ferretmagic/__init__.py
ferretmagic/ferretmagic.py
ferretmagic-20220825.dist-info/LICENSE.md
ferretmagic-20220825.dist-info/METADATA
ferretmagic-20220825.dist-info/WHEEL
ferretmagic-20220825.dist-info/top_level.txt
ferretmagic-20220825.dist-info/RECORD
