Metadata-Version: 2.1
Name: ferretmagic
Version: 20220825
Summary: ipython extension for pyferret
Home-page: https://github.com/PBrockmann/ipython_ferretmagic
Download-URL: https://github.com/PBrockmann/ipython_ferretmagic/tarball/master
Author: Patrick Brockmann
Author-email: Patrick.Brockmann@lsce.ipsl.fr
Keywords: jupyter,ipython,ferret,pyferret,magic,extension
Classifier: Programming Language :: Python :: 3
Classifier: License :: OSI Approved :: MIT License
Classifier: Operating System :: OS Independent
Classifier: Framework :: Jupyter
Classifier: Framework :: IPython
License-File: LICENSE.md
